jdTranslationHelper/__init__.py
jdTranslationHelper/py.typed
jdTranslationHelper-3.3.dist-info/LICENSE
jdTranslationHelper-3.3.dist-info/METADATA
jdTranslationHelper-3.3.dist-info/WHEEL
jdTranslationHelper-3.3.dist-info/top_level.txt
jdTranslationHelper-3.3.dist-info/RECORD
