Metadata-Version: 2.1
Name: jdTranslationHelper
Version: 3.3
Summary: A simple API for translating your programs
Author-email: JakobDev <jakobdev@gmx.de>
License: BSD-2-Clause
Project-URL: Issues, https://codeberg.org/JakobDev/jdTranslationHelper/issues
Project-URL: Source, https://codeberg.org/JakobDev/jdTranslationHelper
Project-URL: Donation, https://ko-fi.com/jakobdev
Keywords: JakobDev,translation,localization
Classifier: Development Status :: 5 - Production/Stable
Classifier: Intended Audience :: Developers
Classifier: Environment :: Other Environment
Classifier: License :: OSI Approved :: BSD License
Classifier: Topic :: Software Development :: Libraries :: Python Modules
Classifier: Operating System :: OS Independent
Classifier: Operating System :: POSIX
Classifier: Operating System :: POSIX :: BSD
Classifier: Operating System :: POSIX :: Linux
Classifier: Operating System :: MacOS :: MacOS X
Classifier: Operating System :: Microsoft :: Windows
Classifier: Programming Language :: Python :: 3
Classifier: Programming Language :: Python :: 3.8
Classifier: Programming Language :: Python :: 3.9
Classifier: Programming Language :: Python :: 3.10
Classifier: Programming Language :: Python :: 3.11
Classifier: Programming Language :: Python :: 3 :: Only
Classifier: Programming Language :: Python :: Implementation :: CPython
Classifier: Programming Language :: Python :: Implementation :: PyPy
Classifier: Typing :: Typed
Requires-Python: >=3.8
License-File: LICENSE
